masterclass/__init__.py
masterclass/singleton.py
masterclass-0.1.0.dist-info/METADATA
masterclass-0.1.0.dist-info/WHEEL
masterclass-0.1.0.dist-info/RECORD
