Metadata-Version: 2.3
Name: masterclass
Version: 0.1.0
Summary: Definitive Python singleton implementation
Author: Danny Stewart
Author-email: danny@stewart.cc
Requires-Python: >=3.12
Classifier: Programming Language :: Python :: 3
Classifier: Programming Language :: Python :: 3.12
Classifier: Programming Language :: Python :: 3.13
